Metadata-Version: 2.1
Name: github-release-ci
Version: 0.0.18
Summary: Deployment script for github aimed at using CI
Home-page: https://github.com/hiroaki-yamamoto/github_release_ci
Author: Hiroaki Yamamoto
Author-email: hiroaki@hysoftware.net
License: MIT
Keywords: deployment github
Platform: UNKNOWN
Classifier: License :: OSI Approved :: MIT License
Classifier: Programming Language :: Python :: 2.7
Classifier: Programming Language :: Python :: 3.5
